{
  "total": 25,
  "users": [
    {
      "$id": "637cfc9f11007be670af",
      "$createdAt": "2022-11-22T16:45:19.178+00:00",
      "$updatedAt": "2023-01-19T09:26:01.898+00:00",
      "name": "test",
      "password": "$argon2id$v=19$m=65536,t=4,p=3$UjFoVmZNYTEyQWVwMGsvNA$qi9tMWwrqicyMB03ZKybciEKqsfbri5Mupx7Dtc7uao",
      "hash": "argon2",
      "hashOptions": {
        "memoryCost": 2048,
        "timeCost": 4,
        "threads": 3,
        "type": "argon2"
      },
      "registration": "2022-11-22T16:45:19.178+00:00",
      "status": true,
      "passwordUpdate": "2022-11-22T16:45:19.178+00:00",
      "email": "test@test.ca",
      "phone": "",
      "emailVerification": true,
      "phoneVerification": false,
      "prefs": {}
    },
    {
      "$id": "6380299b72dae0323dcf",
      "$createdAt": "2022-11-25T02:34:03.579+00:00",
      "$updatedAt": "2023-02-20T00:22:42.054+00:00",
      "name": "Quang",
      "password": "$argon2id$v=19$m=65536,t=4,p=3$cm51WG1SNm9QeXczeFJVQQ$+0McOEvLk/GrJBLqPtFNAqc5NRTtVWczOxgoaxN1VeQ",
      "hash": "argon2",
      "hashOptions": {
        "type": "argon2",
        "memoryCost": 2048,
        "timeCost": 4,
        "threads": 3
      },
      "registration": "2022-11-25T02:34:03.579+00:00",
      "status": true,
      "passwordUpdate": "2023-02-20T00:22:42.054+00:00",
      "email": "contact.quangtran@gmail.com",
      "phone": "+1234567890",
      "emailVerification": true,
      "phoneVerification": false,
      "prefs": {
        "from": "Montreal, Quebec",
        "myPref": "testinggg testinggg"
      }
    },
    {
      "$id": "63bbca8bc560a411f536",
      "$createdAt": "2023-01-09T08:04:27.914+00:00",
      "$updatedAt": "2023-01-19T09:26:01.917+00:00",
      "name": "davidd",
      "password": "$argon2id$v=19$m=65536,t=4,p=3$VjFxRERTaXRvQVliYzlHaQ$YrDjoIqg5YCkNiMSUa3LTFIhIVrCmJ9n+8d3KV71ycs",
      "hash": "argon2",
      "hashOptions": {
        "memoryCost": 2048,
        "timeCost": 4,
        "threads": 3,
        "type": "argon2"
      },
      "registration": "2023-01-09T08:04:27.914+00:00",
      "status": true,
      "passwordUpdate": "2023-01-09T08:04:27.914+00:00",
      "email": "wibej91503@letpays.com",
      "phone": "",
      "emailVerification": false,
      "phoneVerification": false,
      "prefs": {}
    },
    {
      "$id": "63c96baa687d23de8911",
      "$createdAt": "2023-01-19T16:11:22.532+00:00",
      "$updatedAt": "2023-02-22T00:17:58.224+00:00",
      "name": "Hoda",
      "password": "$argon2id$v=19$m=65536,t=4,p=3$dGVsMmUuQ1U2V0pZTzZMUQ$cpIVwfcL6rRaRksUe78iFtXrzNt+BlnGrf+OsaeJn+A",
      "hash": "argon2",
      "hashOptions": {
        "type": "argon2",
        "memoryCost": 2048,
        "timeCost": 4,
        "threads": 3
      },
      "registration": "2023-01-19T16:11:22.532+00:00",
      "status": true,
      "passwordUpdate": "2023-02-22T00:17:02.559+00:00",
      "email": "hoda_nsh@yahoo.com",
      "phone": "",
      "emailVerification": true,
      "phoneVerification": false,
      "prefs": {}
    },
    {
      "$id": "63c9eb6acc2800870801",
      "$createdAt": "2023-01-20T01:16:26.937+00:00",
      "$updatedAt": "2023-03-06T02:49:37.291+00:00",
      "name": "AliZ",
      "password": "$argon2id$v=19$m=65536,t=4,p=3$a1Z5dVlJUnNsWlZVLnVPcA$hEVgfjt9k5QJg/WrbVHb8Mfz9jnDb/MfB966sGkhi/k",
      "hash": "argon2",
      "hashOptions": {
        "type": "argon2",
        "memoryCost": 2048,
        "timeCost": 4,
        "threads": 3
      },
      "registration": "2023-01-20T01:16:26.937+00:00",
      "status": true,
      "passwordUpdate": "2023-03-06T02:49:37.291+00:00",
      "email": "m.alizahir786@gmail.com",
      "phone": "",
      "emailVerification": true,
      "phoneVerification": false,
      "prefs": {
        "from": "Montreal, Quebec"
      }
    },
    {
      "$id": "63ca3fbd4dfa42d3014f",
      "$createdAt": "2023-01-20T07:16:13.423+00:00",
      "$updatedAt": "2023-01-20T07:16:13.423+00:00",
      "name": "Marwa",
      "password": "$argon2id$v=19$m=65536,t=4,p=3$MkI4Tlk1LlZFcU9WcEZKag$lC3dQ+8lTzGLUMYdOeOWbGN4q1ZSgwEVH7G1xgR4Yhs",
      "hash": "argon2",
      "hashOptions": {
        "type": "argon2",
        "memoryCost": 2048,
        "timeCost": 4,
        "threads": 3
      },
      "registration": "2023-01-20T07:16:13.422+00:00",
      "status": true,
      "passwordUpdate": "2023-01-20T07:16:13.422+00:00",
      "email": "khalidmarwa786@gmail.com",
      "phone": "",
      "emailVerification": false,
      "phoneVerification": false,
      "prefs": {}
    },
    {
      "$id": "63cc81d97bcd2aa75920",
      "$createdAt": "2023-01-22T00:22:49.607+00:00",
      "$updatedAt": "2023-01-22T00:22:49.607+00:00",
      "name": "inti",
      "password": "$argon2id$v=19$m=65536,t=4,p=3$WVEzTkViV2tVV3l2L0IyYw$1oSPDDxRZfm36Y0oIOKKCJbBY6Ymyx3pdTyFjDx1BP8",
      "hash": "argon2",
      "hashOptions": {
        "type": "argon2",
        "memoryCost": 2048,
        "timeCost": 4,
        "threads": 3
      },
      "registration": "2023-01-22T00:22:49.606+00:00",
      "status": true,
      "passwordUpdate": "2023-01-22T00:22:49.606+00:00",
      "email": "intisar.tela@moabuild.com",
      "phone": "",
      "emailVerification": false,
      "phoneVerification": false,
      "prefs": {}
    },
    {
      "$id": "63d5a43c8362e0ca7ed7",
      "$createdAt": "2023-01-28T22:39:56.647+00:00",
      "$updatedAt": "2023-01-29T04:47:06.947+00:00",
      "name": "big_boss_123",
      "password": "$argon2id$v=19$m=65536,t=4,p=3$VHlBL2puTjBqbGhkL1JlMw$Iz45mNjebjxR/qE1Gu3b7yV3sKhg2a77PE8aRtJ5QnI",
      "hash": "argon2",
      "hashOptions": {
        "type": "argon2",
        "memoryCost": 2048,
        "timeCost": 4,
        "threads": 3
      },
      "registration": "2023-01-28T22:39:56.646+00:00",
      "status": true,
      "passwordUpdate": "2023-01-29T04:47:06.947+00:00",
      "email": "lucascatchlove@gmail.com",
      "phone": "",
      "emailVerification": true,
      "phoneVerification": false,
      "prefs": {}
    },
    {
      "$id": "63d5ad3351a68ab27e92",
      "$createdAt": "2023-01-28T23:18:11.434+00:00",
      "$updatedAt": "2023-01-28T23:18:29.603+00:00",
      "name": "Tushar",
      "password": "$argon2id$v=19$m=65536,t=4,p=3$SVJnZzlUZ0tYWFFzRW9LdA$WjbHhK1Qd44WMxIaKZK0L3wduTkr3JIb3YLhOArLq08",
      "hash": "argon2",
      "hashOptions": {
        "type": "argon2",
        "memoryCost": 2048,
        "timeCost": 4,
        "threads": 3
      },
      "registration": "2023-01-28T23:18:11.433+00:00",
      "status": true,
      "passwordUpdate": "2023-01-28T23:18:11.433+00:00",
      "email": "tusharsdropbox@gmail.com",
      "phone": "",
      "emailVerification": true,
      "phoneVerification": false,
      "prefs": {}
    },
    {
      "$id": "63e1450116a4f6ba1b20",
      "$createdAt": "2023-02-06T18:20:49.212+00:00",
      "$updatedAt": "2023-03-05T22:59:11.210+00:00",
      "name": "Tushar Raval",
      "password": "$argon2id$v=19$m=65536,t=4,p=3$NUIycDBIaVllTHZpOWtGNA$6wfW1U8k3My3yqnzs2WvFMoWBgRgtBR+Cqbx82sFJDA",
      "hash": "argon2",
      "hashOptions": {
        "type": "argon2",
        "memoryCost": 2048,
        "timeCost": 4,
        "threads": 3
      },
      "registration": "2023-02-06T18:20:49.212+00:00",
      "status": true,
      "passwordUpdate": "2023-03-05T22:59:11.210+00:00",
      "email": "tushar.raval102@gmail.com",
      "phone": "",
      "emailVerification": true,
      "phoneVerification": false,
      "prefs": {
        "from": "Montreal, QC"
      }
    },
    {
      "$id": "63e475c359645e015103",
      "$createdAt": "2023-02-09T04:25:39.465+00:00",
      "$updatedAt": "2023-02-09T04:25:41.720+00:00",
      "name": "lucasc",
      "password": "$argon2id$v=19$m=65536,t=4,p=3$TlYwaFRSby85TWJwclJ4Qw$UHbqIbRDZW1WgyBvRjAgthdVvEOF+JydTR0e8kXup/M",
      "hash": "argon2",
      "hashOptions": {
        "type": "argon2",
        "memoryCost": 2048,
        "timeCost": 4,
        "threads": 3
      },
      "registration": "2023-02-09T04:25:39.465+00:00",
      "status": true,
      "passwordUpdate": "2023-02-09T04:25:39.465+00:00",
      "email": "d@c.com",
      "phone": "",
      "emailVerification": true,
      "phoneVerification": false,
      "prefs": {}
    },
    {
      "$id": "63ed7cce0f5b4709c2c6",
      "$createdAt": "2023-02-16T00:46:06.162+00:00",
      "$updatedAt": "2023-02-16T00:48:02.031+00:00",
      "name": "lailaalhalabi",
      "password": "$argon2id$v=19$m=65536,t=4,p=3$azQyQkxCQkpBU0ZPUVFPNg$qWhI1dA7RzeOlnj48SKHAIcL6COZrG9xOR19wkbz3dc",
      "hash": "argon2",
      "hashOptions": {
        "type": "argon2",
        "memoryCost": 2048,
        "timeCost": 4,
        "threads": 3
      },
      "registration": "2023-02-16T00:46:06.162+00:00",
      "status": true,
      "passwordUpdate": "2023-02-16T00:46:06.162+00:00",
      "email": "laila.alhalabi99@gmail.com",
      "phone": "",
      "emailVerification": true,
      "phoneVerification": false,
      "prefs": {}
    },
    {
      "$id": "6406fa8f8efc0340f593",
      "$createdAt": "2023-03-07T08:49:19.688+00:00",
      "$updatedAt": "2023-03-07T08:49:36.247+00:00",
      "name": "salehatariq",
      "password": "$argon2id$v=19$m=65536,t=4,p=3$emNrc3JmbXdCOFlSaVMzRA$kLtiGlUzZeL+ftOSinxm83yECJn+iF/JF2YJnabefqg",
      "hash": "argon2",
      "hashOptions": {
        "type": "argon2",
        "memoryCost": 2048,
        "timeCost": 4,
        "threads": 3
      },
      "registration": "2023-03-07T08:49:19.688+00:00",
      "status": true,
      "passwordUpdate": "2023-03-07T08:49:19.688+00:00",
      "email": "s.tar3@hotmail.com",
      "phone": "",
      "emailVerification": true,
      "phoneVerification": false,
      "prefs": {}
    },
    {
      "$id": "64122d5bd7c196d37fa4",
      "$createdAt": "2023-03-15T20:41:00.022+00:00",
      "$updatedAt": "2023-03-15T20:41:00.022+00:00",
      "name": "Ava Brown",
      "password": "$argon2id$v=19$m=65536,t=4,p=3$N1dSNS5mbUovYzlWOGsvMA$6XUQGM24TFfWPu9pBMz9/M+l6Yjzlj+pVTbAUhXPifk",
      "hash": "argon2",
      "hashOptions": {
        "type": "argon2",
        "memoryCost": 2048,
        "timeCost": 4,
        "threads": 3
      },
      "registration": "2023-03-15T20:41:00.021+00:00",
      "status": true,
      "passwordUpdate": "2023-03-15T20:41:00.021+00:00",
      "email": "ava.brown123@example.com",
      "phone": "",
      "emailVerification": false,
      "phoneVerification": false,
      "prefs": {}
    },
    {
      "$id": "64122d5c2e06454a9f7b",
      "$createdAt": "2023-03-15T20:41:00.290+00:00",
      "$updatedAt": "2023-03-15T20:41:00.290+00:00",
      "name": "Benjamin Davis",
      "password": "$argon2id$v=19$m=65536,t=4,p=3$UmFMUk90Q0gxRXZMQTlUbQ$DU9SLOz4YeOlUl/ME0GofOd9xEJtPbM/yjqRI3WeB80",
      "hash": "argon2",
      "hashOptions": {
        "type": "argon2",
        "memoryCost": 2048,
        "timeCost": 4,
        "threads": 3
      },
      "registration": "2023-03-15T20:41:00.290+00:00",
      "status": true,
      "passwordUpdate": "2023-03-15T20:41:00.290+00:00",
      "email": "benjamin.davis456@example.com",
      "phone": "",
      "emailVerification": false,
      "phoneVerification": false,
      "prefs": {}
    },
    {
      "$id": "64122d5c5980881e8726",
      "$createdAt": "2023-03-15T20:41:00.466+00:00",
      "$updatedAt": "2023-03-15T20:41:00.466+00:00",
      "name": "Charlotte Rodriguez",
      "password": "$argon2id$v=19$m=65536,t=4,p=3$WTJYNHpoYkZzRnl1NUQ3ZQ$0u9MR9Ihtig2DVRgEx+Z/YvwrW6XcDxhvHl58NTjuIY",
      "hash": "argon2",
      "hashOptions": {
        "type": "argon2",
        "memoryCost": 2048,
        "timeCost": 4,
        "threads": 3
      },
      "registration": "2023-03-15T20:41:00.466+00:00",
      "status": true,
      "passwordUpdate": "2023-03-15T20:41:00.466+00:00",
      "email": "charlotte.rodriguez789@example.com",
      "phone": "",
      "emailVerification": false,
      "phoneVerification": false,
      "prefs": {}
    },
    {
      "$id": "64122d5c8520198e2b02",
      "$createdAt": "2023-03-15T20:41:00.647+00:00",
      "$updatedAt": "2023-03-15T20:41:00.647+00:00",
      "name": "David Martinez",
      "password": "$argon2id$v=19$m=65536,t=4,p=3$UkxFRXJLVjFxSE10aWFHUw$r84edQEwNE5L+Rg5coIaPFUJRuLNWk+7fznKZK15wr4",
      "hash": "argon2",
      "hashOptions": {
        "type": "argon2",
        "memoryCost": 2048,
        "timeCost": 4,
        "threads": 3
      },
      "registration": "2023-03-15T20:41:00.646+00:00",
      "status": true,
      "passwordUpdate": "2023-03-15T20:41:00.646+00:00",
      "email": "david.martinez234@example.com",
      "phone": "",
      "emailVerification": false,
      "phoneVerification": false,
      "prefs": {}
    },
    {
      "$id": "64122d5cac883fea60d3",
      "$createdAt": "2023-03-15T20:41:00.808+00:00",
      "$updatedAt": "2023-03-15T20:41:00.808+00:00",
      "name": "Emily Hernandez",
      "password": "$argon2id$v=19$m=65536,t=4,p=3$UnNvdzFNc3Z2eDZhLjU4Ng$RK2aUPkqv8dSF+yYL0F64WNr2zRGiQTBDPKQqFkz2Xg",
      "hash": "argon2",
      "hashOptions": {
        "type": "argon2",
        "memoryCost": 2048,
        "timeCost": 4,
        "threads": 3
      },
      "registration": "2023-03-15T20:41:00.808+00:00",
      "status": true,
      "passwordUpdate": "2023-03-15T20:41:00.808+00:00",
      "email": "emily.hernandez567@example.com",
      "phone": "",
      "emailVerification": false,
      "phoneVerification": false,
      "prefs": {}
    },
    {
      "$id": "64122d5cd716ee142a3f",
      "$createdAt": "2023-03-15T20:41:00.980+00:00",
      "$updatedAt": "2023-03-15T20:41:00.980+00:00",
      "name": "Finn Smith",
      "password": "$argon2id$v=19$m=65536,t=4,p=3$dnRMU1FCaDBCT1pUTllDRg$hWDF8Gcmk2AP/o0oFWuNWIq/4QJGr0Dk4kvaZxyuJ+w",
      "hash": "argon2",
      "hashOptions": {
        "type": "argon2",
        "memoryCost": 2048,
        "timeCost": 4,
        "threads": 3
      },
      "registration": "2023-03-15T20:41:00.980+00:00",
      "status": true,
      "passwordUpdate": "2023-03-15T20:41:00.979+00:00",
      "email": "finn.smith890@example.com",
      "phone": "",
      "emailVerification": false,
      "phoneVerification": false,
      "prefs": {}
    },
    {
      "$id": "64122d5d11469462207d",
      "$createdAt": "2023-03-15T20:41:01.170+00:00",
      "$updatedAt": "2023-03-15T20:41:01.170+00:00",
      "name": "Gabriela Garcia",
      "password": "$argon2id$v=19$m=65536,t=4,p=3$TkU5Z3RnRlpHWTFkU3A5dw$Yc+yN47hVNjNjlsVxhLmS/RxnNsqh447kroLt+M/seg",
      "hash": "argon2",
      "hashOptions": {
        "type": "argon2",
        "memoryCost": 2048,
        "timeCost": 4,
        "threads": 3
      },
      "registration": "2023-03-15T20:41:01.169+00:00",
      "status": true,
      "passwordUpdate": "2023-03-15T20:41:01.169+00:00",
      "email": "gabriela.garcia123@example.com",
      "phone": "",
      "emailVerification": false,
      "phoneVerification": false,
      "prefs": {}
    },
    {
      "$id": "64122d5d3b705750006c",
      "$createdAt": "2023-03-15T20:41:01.348+00:00",
      "$updatedAt": "2023-03-15T20:41:01.348+00:00",
      "name": "Henry Wilson",
      "password": "$argon2id$v=19$m=65536,t=4,p=3$YkpqWkxlOHFjVzVKa3dIdA$fUD/wrn1DN5Nj0DO7RRsUj1lo+wzeBciCuHeLbOnNFU",
      "hash": "argon2",
      "hashOptions": {
        "type": "argon2",
        "memoryCost": 2048,
        "timeCost": 4,
        "threads": 3
      },
      "registration": "2023-03-15T20:41:01.348+00:00",
      "status": true,
      "passwordUpdate": "2023-03-15T20:41:01.348+00:00",
      "email": "henry.wilson456@example.com",
      "phone": "",
      "emailVerification": false,
      "phoneVerification": false,
      "prefs": {}
    },
    {
      "$id": "64122d5d648374b18017",
      "$createdAt": "2023-03-15T20:41:01.511+00:00",
      "$updatedAt": "2023-03-15T20:41:01.511+00:00",
      "name": "Isabella Lee",
      "password": "$argon2id$v=19$m=65536,t=4,p=3$bUJWM1QuTkYzb0JJZ2ViSg$xAmeFZRovbPu0qHaDjZSv+jEirxxu5p2RbaFTFOjG+Y",
      "hash": "argon2",
      "hashOptions": {
        "type": "argon2",
        "memoryCost": 2048,
        "timeCost": 4,
        "threads": 3
      },
      "registration": "2023-03-15T20:41:01.511+00:00",
      "status": true,
      "passwordUpdate": "2023-03-15T20:41:01.511+00:00",
      "email": "isabella.lee789@example.com",
      "phone": "",
      "emailVerification": false,
      "phoneVerification": false,
      "prefs": {}
    },
    {
      "$id": "64122d5d8dd3645e377a",
      "$createdAt": "2023-03-15T20:41:01.689+00:00",
      "$updatedAt": "2023-03-15T20:41:01.689+00:00",
      "name": "Jacob Perez",
      "password": "$argon2id$v=19$m=65536,t=4,p=3$Z05WalRpd3VlNTNKOFRyRQ$w7UXlvZH7xuCDjn4zPqTnGpshUYK+18YI3+ylytodhc",
      "hash": "argon2",
      "hashOptions": {
        "type": "argon2",
        "memoryCost": 2048,
        "timeCost": 4,
        "threads": 3
      },
      "registration": "2023-03-15T20:41:01.689+00:00",
      "status": true,
      "passwordUpdate": "2023-03-15T20:41:01.689+00:00",
      "email": "jacob.perez234@example.com",
      "phone": "",
      "emailVerification": false,
      "phoneVerification": false,
      "prefs": {}
    },
    {
      "$id": "6412b7fd63c9c63443a3",
      "$createdAt": "2023-03-16T06:32:29.511+00:00",
      "$updatedAt": "2023-03-16T06:35:06.621+00:00",
      "name": "M.Ali",
      "password": "$argon2id$v=19$m=65536,t=4,p=3$Z3FELzhPT2RxMUc1UUk1SQ$362kSXhTY2ZUCrgcVe4YvBIflmWh/sGz1MtT/NVS++4",
      "hash": "argon2",
      "hashOptions": {
        "type": "argon2",
        "memoryCost": 2048,
        "timeCost": 4,
        "threads": 3
      },
      "registration": "2023-03-16T06:32:29.511+00:00",
      "status": true,
      "passwordUpdate": "2023-03-16T06:32:29.511+00:00",
      "email": "ali_4z@hotmail.com",
      "phone": "",
      "emailVerification": true,
      "phoneVerification": false,
      "prefs": {
        "from": "Montreal, Quebec"
      }
    },
    {
      "$id": "6414f71a243677a72a85",
      "$createdAt": "2023-03-17T23:26:18.271+00:00",
      "$updatedAt": "2023-03-17T23:46:52.970+00:00",
      "name": "SamyG",
      "password": "$argon2id$v=19$m=65536,t=4,p=3$RTdBaDdHaFpTVm53Sld2SQ$4TzLbiA4rGos/Tl90tqb5BYdS2r/Zqc14JYeh0oDBaY",
      "hash": "argon2",
      "hashOptions": {
        "type": "argon2",
        "memoryCost": 2048,
        "timeCost": 4,
        "threads": 3
      },
      "registration": "2023-03-17T23:26:18.270+00:00",
      "status": true,
      "passwordUpdate": "2023-03-17T23:26:18.270+00:00",
      "email": "samantha.guillemette@gmail.com",
      "phone": "",
      "emailVerification": true,
      "phoneVerification": false,
      "prefs": {}
    }
  ]
}
